DESCRIPTION.rst
MANIFEST.in
README.md
doc-requirements.txt
pylintrc
setup.cfg
setup.py
test-requirements.txt
tox.ini
versioneer.py
docs/API.rst
docs/Makefile
docs/conf.py
docs/index.rst
docs/make.bat
docs/_static/.empty
magnetic/__init__.py
magnetic/_utils.py
magnetic/_version.py
magnetic/asyncore.py
magnetic.egg-info/PKG-INFO
magnetic.egg-info/SOURCES.txt
magnetic.egg-info/dependency_links.txt
magnetic.egg-info/requires.txt
magnetic.egg-info/top_level.txt
magnetic/_internals/__init__.py
magnetic/_internals/inetd.py
magnetic/_internals/launchd.py
magnetic/_internals/sane_fromfd.py
magnetic/_internals/sane_fromfd_build.py
magnetic/_internals/sock_enums.py
magnetic/_internals/systemd.py
tests/conftest.py
tests/test_utils.py